CHANGES.txt
DEPENDENCES.txt
README.txt
setup.py
src/ng/__init__.py
src/ng.site.greenpsy.egg-info/PKG-INFO
src/ng.site.greenpsy.egg-info/SOURCES.txt
src/ng.site.greenpsy.egg-info/dependency_links.txt
src/ng.site.greenpsy.egg-info/namespace_packages.txt
src/ng.site.greenpsy.egg-info/not-zip-safe
src/ng.site.greenpsy.egg-info/requires.txt
src/ng.site.greenpsy.egg-info/top_level.txt
src/ng/site/__init__.py
src/ng/site/greenpsy/__init__.py
src/ng/site/greenpsy/configure.zcml
src/ng/site/greenpsy/ng.site.greenpsy.txt
src/ng/site/greenpsy/etc/ng.site.greenpsy-configure.zcml
src/ng/site/greenpsy/etc/ng.site.greenpsy-meta.zcml
src/ng/site/greenpsy/install/__init__.py
src/ng/site/greenpsy/install/configure.zcml