Metadata-Version: 1.0
Name: ng.site.greenpsy
Version: 1.0.0
Summary: Site for greenpsy community
Home-page: http://dreambot.ru/dreambotsite/ng.site.greenpsy/
Author: Andrey Orlov
Author-email: dbdt@dreambot.ru
License: GPL v2.1
Platform: UNKNOWN
Classifier: Environment :: Web Environment
Classifier: Intended Audience :: Developers
Classifier: License :: OSI Approved :: GNU General Public License (GPL)
Classifier: Programming Language :: Python
Classifier: Operating System :: OS Independent
Classifier: Topic :: Internet :: WWW/HTTP
Classifier: Framework :: Zope3
